pydropper/__init__.py
pydropper/env.py
pydropper/main.py
pydropper/server/__init__.py
pydropper/server/funcs.py
pydropper/server/server_main.py
pydropper-0.1.3.dist-info/LICENSE
pydropper-0.1.3.dist-info/METADATA
pydropper-0.1.3.dist-info/WHEEL
pydropper-0.1.3.dist-info/RECORD
