Metadata-Version: 2.1
Name: PyDropper
Version: 0.1.3
Summary: 
Author: jiho7407
Requires-Python: >=3.12,<4.0
Classifier: Programming Language :: Python :: 3
Classifier: Programming Language :: Python :: 3.12
Requires-Dist: aiofiles (>=23.2.1,<24.0.0)
Requires-Dist: fastapi (>=0.110.1,<0.111.0)
Requires-Dist: httpx (>=0.27.0,<0.28.0)
Requires-Dist: python-multipart (>=0.0.9,<0.0.10)
Requires-Dist: uvicorn[standard] (>=0.29.0,<0.30.0)
